MANIFEST.in
setup.cfg
setup.py
ipytracer/__init__.py
ipytracer/_version.py
ipytracer/model.py
ipytracer/tracer.py
ipytracer/utils.py
ipytracer/view.py
ipytracer.egg-info/PKG-INFO
ipytracer.egg-info/SOURCES.txt
ipytracer.egg-info/dependency_links.txt
ipytracer.egg-info/not-zip-safe
ipytracer.egg-info/requires.txt
ipytracer.egg-info/top_level.txt
ipytracer/static/extension.js
ipytracer/static/index.js
ipytracer/static/index.js.map
ipytracer/staticlab/ipytracer.bundle.js
ipytracer/staticlab/ipytracer.bundle.js.manifest